{"examples_backtop_index.md":"255a15e1","guide_details.md":"2ad143b5","examples_breadcrumb_index.md":"91f5122c","examples_result_index.md":"3db4ed42","examples_spin_index.md":"9c0430d6","index.md":"b3eb9300","guide_log.md":"0ccfdc38","guide_start.md":"09592048","examples_dropdown_index.md":"ed524c1e","examples_button_index.md":"d0a704f6","examples_link_index.md":"74799b9b","examples_progress_index.md":"56247360","examples_grid_index.md":"a9eb6c83","examples_switch_index.md":"0c5c5b22","examples_layout_index.md":"bc7dce4b","examples_menu_index.md":"863b604e","examples_modal_index.md":"e1960bbf","examples_icon_index.md":"add0f620"}
