{"examples_alert_index.md":"2cf494a9","guide_details.md":"f79470e6","examples_button_index.md":"cbe07fb4","examples_backtop_index.md":"a7e1a3ed","index.md":"d82f56b3","guide_start.md":"1667d210","examples_layout_index.md":"b79b86d1","examples_link_index.md":"cbf59ec9","examples_menu_index.md":"63cca1ba","guide_log.md":"a7d4378e","examples_card_index.md":"f74b6734","examples_result_index.md":"f3dcaa47","examples_breadcrumb_index.md":"5f87d05b","examples_spin_index.md":"78c4fd77","examples_avatar_index.md":"93b77d62","examples_drawer_index.md":"fec5eb6b","examples_progress_index.md":"4bd5e3c9","examples_switch_index.md":"f2c88131","examples_dropdown_index.md":"95eae348","examples_table_index.md":"9071d169","examples_grid_index.md":"8c457d65","examples_modal_index.md":"6188527a","examples_icon_index.md":"1edcedb4"}
